emotion_framework/README.md
emotion_framework/__init__.py
emotion_framework/setup.py
emotion_framework/analyzers/__init__.py
emotion_framework/analyzers/ai_agent.py
emotion_framework/analyzers/fer_analyzer.py
emotion_framework/core/__init__.py
emotion_framework/core/config_loader.py
emotion_framework/core/pipeline.py
emotion_framework/core/realtime_pipeline.py
emotion_framework/models/__init__.py
emotion_framework/models/result_models.py
emotion_framework/processors/__init__.py
emotion_framework/processors/feature_extractors.py
emotion_framework/processors/fusion_engine.py
emotion_framework/processors/realtime_processor.py
emotion_framework/processors/video_processor.py
emotion_framework-1.0.1.dist-info/LICENSE
emotion_framework-1.0.1.dist-info/METADATA
emotion_framework-1.0.1.dist-info/WHEEL
emotion_framework-1.0.1.dist-info/top_level.txt
emotion_framework-1.0.1.dist-info/RECORD
