Metadata-Version: 2.1
Name: emotion-framework
Version: 1.0.1
Summary: Multimodal emotion recognition framework for video analysis
Author-email: Emotion Analysis Team <dogukangundo@emotionanalysis.com>
License: MIT
Project-URL: Homepage, https://github.com/DogukanGun/MetAI
Project-URL: Repository, https://github.com/DogukanGun/MetAI
Project-URL: Bug Tracker, https://github.com/DogukanGun/MetAI/issues
Project-URL: Documentation, https://github.com/DogukanGun/MetAI#readme
Keywords: emotion,recognition,multimodal,video,analysis,deep-learning,AI
Classifier: Development Status :: 4 - Beta
Classifier: Intended Audience :: Developers
Classifier: Intended Audience :: Science/Research
Classifier: Programming Language :: Python :: 3
Classifier: Programming Language :: Python :: 3.8
Classifier: Programming Language :: Python :: 3.9
Classifier: Programming Language :: Python :: 3.10
Classifier: Programming Language :: Python :: 3.11
Classifier: Programming Language :: Python :: 3.12
Classifier: Topic :: Scientific/Engineering :: Artificial Intelligence
Classifier: Topic :: Multimedia :: Video
Requires-Python: >=3.8
License-File: LICENSE
Requires-Dist: torch>=2.2.0
Requires-Dist: torchvision>=0.17.0
Requires-Dist: numpy>=1.26.0
Requires-Dist: scipy>=1.11.0
Requires-Dist: scikit-learn>=1.3.0
Requires-Dist: pytorch-minimize>=0.0.2
Requires-Dist: optuna>=4.5.0
Requires-Dist: xgboost>=3.0.0
Requires-Dist: librosa>=0.10.0
Requires-Dist: opensmile>=2.4.1
Requires-Dist: pyAudioAnalysis>=0.3.14
Requires-Dist: pydub>=0.25.1
Requires-Dist: webrtcvad>=2.0.10
Requires-Dist: soundfile>=0.12.1
Requires-Dist: opencv-python>=4.8.0
Requires-Dist: mediapipe>=0.10.0
Requires-Dist: face-recognition>=1.3.0
Requires-Dist: py-feat>=0.5.0
Requires-Dist: pillow>=10.0.0
Requires-Dist: scikit-image>=0.21.0
Requires-Dist: transformers>=4.30.0
Requires-Dist: sentence-transformers>=2.2.2
Requires-Dist: nltk>=3.8.1
Requires-Dist: spacy>=3.6.0
Requires-Dist: textblob>=0.17.1
Requires-Dist: vaderSentiment>=3.3.2
Requires-Dist: openai>=1.0.0
Requires-Dist: openai-whisper
Requires-Dist: moviepy>=1.0.3
Requires-Dist: ffmpeg-python>=0.2.0
Requires-Dist: pandas>=2.0.3
Requires-Dist: matplotlib>=3.7.2
Requires-Dist: seaborn>=0.12.2
Requires-Dist: plotly>=5.15.0
Requires-Dist: tqdm>=4.65.0
Requires-Dist: PyYAML>=6.0.1
Requires-Dist: python-dotenv>=1.0.0
Requires-Dist: numba>=0.56.0
Requires-Dist: yacs>=0.1.8
Requires-Dist: g2p-en>=2.1.0
Requires-Dist: jieba>=0.42.1
Requires-Dist: pypinyin>=0.47.0
Requires-Dist: pypinyin-dict>=0.1.0
Provides-Extra: dev
Requires-Dist: pytest>=6.0.0; extra == "dev"
Requires-Dist: black>=21.0; extra == "dev"
Requires-Dist: pytest-cov>=4.0.0; extra == "dev"
Requires-Dist: flake8>=6.0.0; extra == "dev"
